apt/__init__.py
apt_py-0.0.1.dist-info/LICENSE
apt_py-0.0.1.dist-info/METADATA
apt_py-0.0.1.dist-info/WHEEL
apt_py-0.0.1.dist-info/top_level.txt
apt_py-0.0.1.dist-info/RECORD
