Metadata-Version: 2.1
Name: apt-py
Version: 0.0.1
Summary: A package for research into asset pricing and backtesting of investment strategies
Home-page: https://github.com/vanBrakel/AssetPricingToolbox
Author: Jean-Paul van Brakel
Author-email: jeanpaulvbrakel@gmail.com
License: UNKNOWN
Platform: UNKNOWN
Classifier: Programming Language :: Python :: 3
Classifier: License :: OSI Approved :: MIT License
Classifier: Operating System :: OS Independent
Requires-Python: >=3.6
